<?xml version="1.0" encoding="UTF-8" ?>
<!DOCTYPE generatorConfiguration PUBLIC "-//mybatis.org//DTD MyBatis Generator Configuration 1.0//EN" "http://mybatis.org/dtd/mybatis-generator-config_1_0.dtd" >
<generatorConfiguration >
    <classPathEntry  location="D:/repository/mysql/mysql-connector-java/5.1.5/mysql-connector-java-5.1.5.jar"/> 
  <context id="context1" >
      
    <jdbcConnection driverClass="com.mysql.jdbc.Driver" connectionURL="jdbc:mysql://139.129.205.176:3306/aaread" userId="aaread" password="aaread123" />
    <javaModelGenerator targetPackage="com.aaread.model" targetProject="aaread" />
    <sqlMapGenerator targetPackage="com.aaread.mapper" targetProject="aaread" />
    <javaClientGenerator targetPackage="com.aaread.mapper" targetProject="aaread" type="XMLMAPPER" />
    
    <table tableName="article"  enableCountByExample="true" enableUpdateByExample="false" enableDeleteByExample="false" 
    enableSelectByExample="true" selectByExampleQueryId="false" ></table>
    <table tableName="content"  enableCountByExample="true" enableUpdateByExample="false" enableDeleteByExample="false" 
    enableSelectByExample="true" selectByExampleQueryId="false" ></table>
    <table tableName="dianzan"  enableCountByExample="true" enableUpdateByExample="false" enableDeleteByExample="false" 
    enableSelectByExample="true" selectByExampleQueryId="false" ></table>
    <table tableName="dingyue"  enableCountByExample="true" enableUpdateByExample="false" enableDeleteByExample="false" 
    enableSelectByExample="true" selectByExampleQueryId="false" ></table>
    <table tableName="fenzhan"  enableCountByExample="true" enableUpdateByExample="false" enableDeleteByExample="false" 
    enableSelectByExample="true" selectByExampleQueryId="false" ></table>
    <table tableName="iorder"  enableCountByExample="true" enableUpdateByExample="false" enableDeleteByExample="false" 
    enableSelectByExample="true" selectByExampleQueryId="false" ></table>
    <table tableName="msg"  enableCountByExample="true" enableUpdateByExample="false" enableDeleteByExample="false" 
    enableSelectByExample="true" selectByExampleQueryId="false" ></table>
    <table tableName="topic"  enableCountByExample="true" enableUpdateByExample="false" enableDeleteByExample="false" 
    enableSelectByExample="true" selectByExampleQueryId="false" ></table>
    <table tableName="users"  enableCountByExample="true" enableUpdateByExample="false" enableDeleteByExample="false" 
    enableSelectByExample="true" selectByExampleQueryId="false" ></table>
    <table tableName="water"  enableCountByExample="true" enableUpdateByExample="false" enableDeleteByExample="false" 
    enableSelectByExample="true" selectByExampleQueryId="false" ></table>
    
  </context>
</generatorConfiguration>